yades_api/__init__.py
yades_api/__main__.py
yades_api/app.py
yades_api/helpers.py
yades_api/middlewares.py
yades_api/routes.py
yades_api/views.py
yades_api-0.0.1.dist-info/METADATA
yades_api-0.0.1.dist-info/WHEEL
yades_api-0.0.1.dist-info/entry_points.txt
yades_api-0.0.1.dist-info/top_level.txt
yades_api-0.0.1.dist-info/RECORD
