Metadata-Version: 2.1
Name: yades-api
Version: 0.0.1
Summary: UNKNOWN
Home-page: https://github.com/yades/yades-api/
Author: Ivan Khomutov
Author-email: i.khomutov@protonmail.com
License: MIT
Keywords: aiohttp asyncio
Platform: UNKNOWN
Classifier: License :: OSI Approved :: MIT License
Classifier: Programming Language :: Python
Classifier: Programming Language :: Python :: 3
Classifier: Programming Language :: Python :: 3.5
Classifier: Programming Language :: Python :: 3.6
Classifier: Programming Language :: Python :: 3.7
Classifier: Programming Language :: Python :: 3.8
Classifier: Topic :: Internet
Classifier: Topic :: Software Development :: Libraries
Classifier: Topic :: Software Development :: Libraries :: Python Modules
Requires-Dist: aiohttp (==3.6.2)
Requires-Dist: dnspython (==1.16.0)
Requires-Dist: environs (==7.4.0)
Requires-Dist: motor (==2.1.0)
